aea_test_autonomy/__init__.py
aea_test_autonomy/configurations.py
aea_test_autonomy/fixture_helpers.py
aea_test_autonomy/py.typed
aea_test_autonomy/base_test_classes/__init__.py
aea_test_autonomy/base_test_classes/agents.py
aea_test_autonomy/base_test_classes/contracts.py
aea_test_autonomy/data/encrypted_keys.json
aea_test_autonomy/data/ethereum_key_1.txt
aea_test_autonomy/data/ethereum_key_2.txt
aea_test_autonomy/data/ethereum_key_3.txt
aea_test_autonomy/data/ethereum_key_4.txt
aea_test_autonomy/data/ethereum_key_5.txt
aea_test_autonomy/data/ethereum_key_deployer.txt
aea_test_autonomy/docker/__init__.py
aea_test_autonomy/docker/acn_node.py
aea_test_autonomy/docker/amm_net.py
aea_test_autonomy/docker/base.py
aea_test_autonomy/docker/ganache.py
aea_test_autonomy/docker/gnosis_safe_net.py
aea_test_autonomy/docker/registries.py
aea_test_autonomy/docker/tendermint.py
aea_test_autonomy/helpers/__init__.py
aea_test_autonomy/helpers/async_utils.py
aea_test_autonomy/helpers/base.py
aea_test_autonomy/helpers/contracts.py
aea_test_autonomy/helpers/tendermint_utils.py
open_aea_test_autonomy-0.21.6.dist-info/licenses/LICENSE
open_aea_test_autonomy-0.21.6.dist-info/METADATA
open_aea_test_autonomy-0.21.6.dist-info/WHEEL
open_aea_test_autonomy-0.21.6.dist-info/top_level.txt
open_aea_test_autonomy-0.21.6.dist-info/RECORD
