Metadata-Version: 2.4
Name: open-aea-test-autonomy
Version: 0.21.6
Summary: Plugin containing test tools for open-autonomy packages.
Author: Valory AG
License: Apache-2.0
Classifier: Environment :: Console
Classifier: Environment :: Web Environment
Classifier: Development Status :: 3 - Alpha
Classifier: Intended Audience :: Developers
Classifier: License :: OSI Approved :: Apache Software License
Classifier: Natural Language :: English
Classifier: Operating System :: MacOS
Classifier: Operating System :: Microsoft
Classifier: Operating System :: Unix
Classifier: Programming Language :: Python :: 3.10
Classifier: Programming Language :: Python :: 3.11
Classifier: Topic :: Communications
Classifier: Topic :: Internet
Classifier: Topic :: Software Development
License-File: LICENSE
Requires-Dist: open-aea[all]<3.0.0,>=2.0.7
Requires-Dist: pytest==7.4.4
Requires-Dist: open-aea-ledger-ethereum<3.0.0,>=2.0.7
Requires-Dist: docker==7.1.0
Dynamic: author
Dynamic: classifier
Dynamic: description
Dynamic: description-content-type
Dynamic: license
Dynamic: license-file
Dynamic: requires-dist
Dynamic: summary
